{
    "code": 0,
    "message": "",
    "resultJson": [
        {
            "id": 16103,
            "name": "渔香圆",
            "memberId": 0,
            "address": "广州黄埔区南湾大街15-16号档(近南湾)",
            "tel": "13922183728",
            "lng": 113.519733217,
            "lat": 23.083563377821,
            "photo": "/upload/shop/20141219130706/13815317pic01.jpg;/upload/shop/1445417273028.png;/upload/shop/1445417276310.png;/upload/shop/1445417279923.png;/upload/shop/1445417283694.png;",
            "logo": "/upload/shop/20141219130706/13815317logo.jpg",
            "createTime": "Dec 22, 2014 12:48:27 PM",
            "discount": "暂无优惠",
            "star": 4,
            "buyOpenStatus": 0,
            "status": 1,
            "isTakeaway": 0,
            "isReserve": 0,
            "typeId": 14,
            "provice": "广东省",
            "city": "广州市",
            "region": "黄埔区",
            "seating": 0,
            "favorite": 0,
            "good": 0,
            "bad": 0,
            "hot": 0,
            "typeName": "粤菜",
            "isOpenRemark": 0,
            "isOpenInvoice": 0,
            "isOpenLinePay": 0,
            "bizType": 1,
            "businesscircle": "夏园",
            "rating": 3.7,
            "personPay": 0,
            "waitTime": 5
        },
        {
            "id": 17002,
            "name": "湘攸木桶饭",
            "memberId": 0,
            "address": "广州黄埔区黄浦区宏光路",
            "tel": "020-22945589",
            "lng": 113.54902512318,
            "lat": 23.114747623538,
            "photo": "/upload/shop/1445396993099.png;/upload/shop/1445396996356.png;/upload/shop/1445396999827.png;/upload/shop/1445397002839.png;/upload/shop/1445397007340.png;/upload/shop/1445397009983.png;",
            "createTime": "Dec 22, 2014 12:48:40 PM",
            "discount": "暂无优惠",
            "star": 4,
            "buyOpenStatus": 0,
            "status": 1,
            "isTakeaway": 0,
            "isReserve": 0,
            "typeId": 12,
            "provice": "广东省",
            "city": "广州市",
            "region": "黄埔区",
            "seating": 0,
            "favorite": 0,
            "good": 0,
            "bad": 0,
            "hot": 0,
            "typeName": "小吃快餐",
            "isOpenRemark": 0,
            "isOpenInvoice": 0,
            "isOpenLinePay": 0,
            "bizType": 1,
            "businesscircle": "开发区东区",
            "rating": 3.6,
            "personPay": 0,
            "waitTime": 5
        },
        {
            "id": 17055,
            "name": "益品火锅",
            "memberId": 0,
            "address": "广州南沙区丰泽西路4号(进港大道口南侧)",
            "tel": "020-39072866",
            "lng": 113.53060932502,
            "lat": 23.066135952041,
            "photo": "/upload/shop/1446023425833.png;/upload/shop/1446023430218.png;/upload/shop/1446023434181.png;/upload/shop/1446023437916.png;",
            "logo": "/upload/shop/20151028171039_logo.png",
            "createTime": "Dec 22, 2014 12:48:40 PM",
            "discount": "暂无优惠",
            "star": 4,
            "buyOpenStatus": 0,
            "status": 1,
            "isTakeaway": 0,
            "isReserve": 0,
            "typeId": 3,
            "provice": "广东省",
            "city": "广州市",
            "region": "南沙区",
            "seating": 0,
            "favorite": 0,
            "good": 0,
            "bad": 0,
            "hot": 0,
            "typeName": "火锅",
            "isOpenRemark": 0,
            "isOpenInvoice": 0,
            "isOpenLinePay": 0,
            "bizType": 1,
            "businesscircle": "金州商业区",
            "rating": 4.3,
            "personPay": 0,
            "waitTime": 5
        },
        {
            "id": 16129,
            "name": "雄记艇仔粥",
            "memberId": 0,
            "address": "广州黄埔区石基路528号(猫记)",
            "lng": 113.3962226119,
            "lat": 23.093495004156,
            "photo": "/upload/shop/20141219130706/20665239pic01.jpg;/upload/shop/1445398045054.png;/upload/shop/1445398048216.png;/upload/shop/1445398051223.png;/upload/shop/1445398054562.png;/upload/shop/1445398057877.png;",
            "logo": "/upload/shop/20141219130706/20665239logo.jpg",
            "createTime": "Dec 22, 2014 12:48:27 PM",
            "discount": "暂无优惠",
            "star": 4,
            "buyOpenStatus": 0,
            "status": 1,
            "isTakeaway": 0,
            "isReserve": 0,
            "typeId": 12,
            "provice": "广东省",
            "city": "广州市",
            "region": "黄埔区",
            "seating": 0,
            "favorite": 0,
            "good": 0,
            "bad": 0,
            "hot": 0,
            "typeName": "小吃快餐",
            "isOpenRemark": 0,
            "isOpenInvoice": 0,
            "isOpenLinePay": 0,
            "bizType": 1,
            "businesscircle": "粤菜",
            "rating": 3.7,
            "personPay": 0,
            "waitTime": 5
        },
        {
            "id": 17063,
            "name": "南沙彬记石锅鱼",
            "memberId": 0,
            "address": "广州南沙区南沙街道江南路65号西",
            "tel": "13417544423",
            "lng": 113.58044631208,
            "lat": 22.754204869596,
            "photo": "/upload/shop/1446023708127.png;/upload/shop/1446023710997.png;/upload/shop/1446023714257.png;/upload/shop/1446023718095.png;",
            "logo": "/upload/shop/20151028171532_logo.png",
            "createTime": "Dec 22, 2014 12:48:41 PM",
            "discount": "暂无优惠",
            "star": 4,
            "buyOpenStatus": 0,
            "status": 1,
            "isTakeaway": 0,
            "isReserve": 0,
            "typeId": 3,
            "provice": "广东省",
            "city": "广州市",
            "region": "南沙区",
            "seating": 0,
            "favorite": 0,
            "good": 0,
            "bad": 0,
            "hot": 0,
            "typeName": "火锅",
            "isOpenRemark": 0,
            "isOpenInvoice": 0,
            "isOpenLinePay": 0,
            "bizType": 1,
            "businesscircle": "火锅",
            "rating": 4.3,
            "personPay": 0,
            "waitTime": 5
        },
        {
            "id": 16192,
            "name": "唐茶",
            "memberId": 0,
            "address": "广州黄埔区黄埔东路(近领好广场)",
            "lng": 113.5054140513,
            "lat": 23.089106573451,
            "photo": "/upload/shop/20141219130706/6213282pic01.jpg;/upload/shop/1445411786631.png;/upload/shop/1445411789802.png;/upload/shop/1445411792438.png;/upload/shop/1445411794811.png;/upload/shop/1445411797528.png;",
            "createTime": "Dec 22, 2014 12:48:28 PM",
            "discount": "暂无优惠",
            "star": 4,
            "buyOpenStatus": 0,
            "status": 1,
            "isTakeaway": 0,
            "isReserve": 0,
            "typeId": 12,
            "provice": "广东省",
            "city": "广州市",
            "region": "黄埔区",
            "seating": 0,
            "favorite": 0,
            "good": 0,
            "bad": 0,
            "hot": 0,
            "typeName": "小吃快餐",
            "isOpenRemark": 0,
            "isOpenInvoice": 0,
            "isOpenLinePay": 0,
            "bizType": 1,
            "businesscircle": "面包甜点",
            "rating": 3.45,
            "personPay": 0,
            "waitTime": 5
        },
        {
            "id": 16501,
            "name": "东北人家饺子馆",
            "memberId": 0,
            "address": "广州黄埔区丰乐北路619号丰乐广场",
            "tel": "020-82399906",
            "lng": 113.45927111521,
            "lat": 23.119861371106,
            "photo": "/upload/shop/1445412248719.png;/upload/shop/1445412252998.png;/upload/shop/1445412255899.png;/upload/shop/1445412259233.png;/upload/shop/1445412262312.png;",
            "logo": "/upload/shop/20141219130706/8726735logo.jpg",
            "createTime": "Dec 22, 2014 12:48:32 PM",
            "discount": "暂无优惠",
            "star": 4,
            "buyOpenStatus": 0,
            "status": 1,
            "isTakeaway": 0,
            "isReserve": 0,
            "typeId": 17,
            "provice": "广东省",
            "city": "广州市",
            "region": "黄埔区",
            "seating": 0,
            "favorite": 0,
            "good": 0,
            "bad": 0,
            "hot": 0,
            "typeName": "东北菜",
            "isOpenRemark": 0,
            "isOpenInvoice": 0,
            "isOpenLinePay": 0,
            "bizType": 1,
            "businesscircle": "大沙地",
            "rating": 3.6,
            "personPay": 46,
            "waitTime": 5
        },
        {
            "id": 15936,
            "name": "王的盛筵",
            "memberId": 0,
            "address": "广州市黄埔区南湾大街15-13号(恒信客家王对面南湾美食街，宝夏花园正门对面)",
            "tel": "13649890216",
            "lng": 113.51988091709,
            "lat": 23.087903863372,
            "photo": "/upload/shop/20141219130706/21318068pic02.jpg;/upload/shop/20141219130706/21318068pic03.jpg;/upload/shop/1445406811901.png;/upload/shop/1445406814614.png;/upload/shop/1445406817855.png;/upload/shop/1445406822144.png;",
            "createTime": "Dec 22, 2014 12:48:24 PM",
            "discount": "暂无优惠",
            "star": 4,
            "buyOpenStatus": 0,
            "status": 1,
            "isTakeaway": 0,
            "isReserve": 0,
            "typeId": 14,
            "provice": "广东省",
            "city": "广州市",
            "region": "黄埔区",
            "seating": 0,
            "favorite": 0,
            "good": 0,
            "bad": 0,
            "hot": 0,
            "typeName": "粤菜",
            "isOpenRemark": 0,
            "isOpenInvoice": 0,
            "isOpenLinePay": 0,
            "bizType": 1,
            "rating": 3.6,
            "personPay": 0,
            "waitTime": 5
        },
        {
            "id": 15969,
            "name": "金三顾冒菜",
            "memberId": 0,
            "address": "广州黄埔区黄埔东路298号惠润广场1楼(那波利披萨内)",
            "tel": "020-22195507",
            "lng": 113.46346922736,
            "lat": 23.104844274395,
            "photo": "/upload/shop/1445413003887.png;/upload/shop/1445413010787.png;/upload/shop/1445413014430.png;/upload/shop/1445413017725.png;/upload/shop/1445413027496.png;",
            "logo": "/upload/shop/20141219130706/21012801logo.jpg",
            "createTime": "Dec 22, 2014 12:48:25 PM",
            "discount": "暂无优惠",
            "star": 4,
            "buyOpenStatus": 0,
            "status": 1,
            "isTakeaway": 0,
            "isReserve": 0,
            "typeId": 12,
            "provice": "广东省",
            "city": "广州市",
            "region": "黄埔区",
            "seating": 0,
            "favorite": 0,
            "good": 0,
            "bad": 0,
            "hot": 0,
            "typeName": "小吃快餐",
            "isOpenRemark": 0,
            "isOpenInvoice": 0,
            "isOpenLinePay": 0,
            "bizType": 1,
            "businesscircle": "大沙地",
            "rating": 3.8,
            "personPay": 28,
            "waitTime": 5
        },
        {
            "id": 16262,
            "name": "泡芙时代",
            "memberId": 0,
            "address": "广州黄埔区潮流名店城B2楼B212室铺(万岁旁)",
            "tel": "15360501099",
            "lng": 113.45326927565,
            "lat": 23.109607871191,
            "photo": "/upload/shop/20141219130706/18396028pic01.jpg;/upload/shop/20141219130706/18396028pic03.jpg;/upload/shop/1445415333774.png;/upload/shop/1445415337181.png;/upload/shop/1445415340898.png;/upload/shop/1445415346460.png;",
            "logo": "/upload/shop/20141219130706/18396028logo.jpg",
            "createTime": "Dec 22, 2014 12:48:29 PM",
            "discount": "暂无优惠",
            "star": 4,
            "buyOpenStatus": 0,
            "status": 1,
            "isTakeaway": 0,
            "isReserve": 0,
            "typeId": 12,
            "provice": "广东省",
            "city": "广州市",
            "region": "黄埔区",
            "seating": 0,
            "favorite": 0,
            "good": 0,
            "bad": 0,
            "hot": 0,
            "typeName": "小吃快餐",
            "isOpenRemark": 0,
            "isOpenInvoice": 0,
            "isOpenLinePay": 0,
            "bizType": 1,
            "businesscircle": "大沙地",
            "rating": 3.4,
            "personPay": 0,
            "waitTime": 5
        }
    ]
}